<odoo>
  <data>
    <!-- explicit list view definition -->
<!--
    <record model="ir.ui.view" id="manageleire.list">
      <field name="name">manageleire list</field>
      <field name="model">manageleire.manageleire</field>
      <field name="arch" type="xml">
        <tree>
          <field name="name"/>
          <field name="value"/>
          <field name="value2"/>
        </tree>
      </field>
    </record>
-->

    <!-- actions opening views on models -->
<!--
    <record model="ir.actions.act_window" id="manageleire.action_window">
      <field name="name">manageleire window</field>
      <field name="res_model">manageleire.manageleire</field>
      <field name="view_mode">tree,form</field>
    </record>
-->

    <!-- server action to the one above -->
<!--
    <record model="ir.actions.server" id="manageleire.action_server">
      <field name="name">manageleire server</field>
      <field name="model_id" ref="model_manageleire_manageleire"/>
      <field name="state">code</field>
      <field name="code">
        action = {
          "type": "ir.actions.act_window",
          "view_mode": "tree,form",
          "res_model": model._name,
        }
      </field>
    </record>
-->

    <!-- Top menu item -->
<!--
    <menuitem name="manageleire" id="manageleire.menu_root"/>
-->
    <!-- menu categories -->
<!--
    <menuitem name="Menu 1" id="manageleire.menu_1" parent="manageleire.menu_root"/>
    <menuitem name="Menu 2" id="manageleire.menu_2" parent="manageleire.menu_root"/>
-->
    <!-- actions -->
<!--
    <menuitem name="List" id="manageleire.menu_1_list" parent="manageleire.menu_1"
              action="manageleire.action_window"/>
    <menuitem name="Server to list" id="manageleire" parent="manageleire.menu_2"
              action="manageleire.action_server"/>
-->
  </data>
</odoo>